orloge/__init__.py
orloge/base.py
orloge/cbc.py
orloge/constants.py
orloge/cplex.py
orloge/cpsat.py
orloge/gurobi.py
orloge-0.18.3.dist-info/METADATA
orloge-0.18.3.dist-info/WHEEL
orloge-0.18.3.dist-info/top_level.txt
orloge-0.18.3.dist-info/RECORD
