Metadata-Version: 2.2
Name: orloge
Version: 0.18.3
Summary: OR log extractor
Author-email: Franco Peschiera <pchtsp@gmail.com>
Maintainer-email: Franco Peschiera <pchtsp@gmail.com>
Project-URL: source, https://github.com/pchtsp/orloge
Project-URL: download, https://github.com/pchtsp/orloge/archive/master.zip
Keywords: Mathematical,Optimization,solver,log,parser
Classifier: Programming Language :: Python
Classifier: Topic :: Software Development
Classifier: Topic :: Software Development :: Libraries
Classifier: Topic :: Software Development :: Libraries :: Python Modules
Requires-Python: >=3.10
Requires-Dist: pandas
Requires-Dist: cpsat-logutils
